{
    "title": "Memo",
    "description": "Discover how works the explorer, transactions, memos, and how to use them on the XRP Ledger.",
    "sections": [
        {
            "type": "title",
            "value": "Part 1: Explorer"
        },
        {
            "type": "body",
            "value": "Copy and past your address in the explorer. Look at the past transactions and search for a transaction with a memo."
        },
        {
            "type": "link",
            "value": "https://testnet.xrpl.org/"
        },
        {
            "type": "title",
            "value": "Part 2: Wallet"
        },
        {
            "type": "body",
            "value": "Install a browser wallet and import your wallet with the private key."
        },
        {
            "type": "link",
            "value": "https://xaman.app/"
        },
        {
            "type": "link",
            "value": "https://gemwallet.app/"
        },
        {
            "type": "link",
            "value": "https://crossmark.io/"
        },
        {
            "type": "title",
            "value": "Part 3: Transaction"
        },
        {
            "type": "body",
            "value": "Follow the instructions in the memo and send the transaction."
        }
    ]
}